singapore_nric_generator/__init__.py
singapore_nric_generator/_internal.py
singapore_nric_generator/core.py
singapore_nric_generator-0.1.1.dist-info/METADATA
singapore_nric_generator-0.1.1.dist-info/WHEEL
singapore_nric_generator-0.1.1.dist-info/RECORD
